ta_signals/__init__.py
ta_signals/main.py
ta_signals-0.0.59.dist-info/LICENSE
ta_signals-0.0.59.dist-info/METADATA
ta_signals-0.0.59.dist-info/WHEEL
ta_signals-0.0.59.dist-info/top_level.txt
ta_signals-0.0.59.dist-info/RECORD
