Metadata-Version: 2.1
Name: ta-signals
Version: 0.0.59
Summary: identify market signals
Home-page: http://github.com/pbringetto/ta.signals
Author: Paul Bringetto
Author-email: plbriqto@gmail.com
Project-URL: Bug Tracker, http://github.com/pbringetto/ta.signals/issues
Classifier: Programming Language :: Python :: 3
Classifier: License :: OSI Approved :: MIT License
Classifier: Operating System :: OS Independent
Requires-Python: >=3.6
License-File: LICENSE
Requires-Dist: pandas
Requires-Dist: pandas-ta
Requires-Dist: numpy
Requires-Dist: scipy
Requires-Dist: python-math
